oae/__init__.py
oae/_nbdev.py
oae/core.py
oae/optimizer.py
oae/tree.py
oae-0.0.1.dist-info/LICENSE
oae-0.0.1.dist-info/METADATA
oae-0.0.1.dist-info/WHEEL
oae-0.0.1.dist-info/entry_points.txt
oae-0.0.1.dist-info/top_level.txt
oae-0.0.1.dist-info/RECORD
