Metadata-Version: 2.1
Name: oae
Version: 0.0.1
Summary: Optimal Action Extraction for Random Forests and Boosted Trees
Home-page: https://github.com/numb3r33/oae/tree/master/
Author: Abhishek Sharma
Author-email: numb3r33@gmail.com
License: Apache Software License 2.0
Keywords: ILP
Platform: UNKNOWN
Classifier: Development Status :: 3 - Alpha
Classifier: Intended Audience :: Developers
Classifier: License :: OSI Approved :: Apache Software License
Classifier: Natural Language :: English
Classifier: Programming Language :: Python :: 3.6
Classifier: Programming Language :: Python :: 3.7
Classifier: Programming Language :: Python :: 3.8
Requires-Python: >=3.6
Requires-Dist: appnope (==0.1.0)
Requires-Dist: attrs (==19.3.0)
Requires-Dist: backcall (==0.1.0)
Requires-Dist: bleach (==3.1.5)
Requires-Dist: cffi (==1.14.0)
Requires-Dist: decorator (==4.4.2)
Requires-Dist: defusedxml (==0.6.0)
Requires-Dist: ecos (==2.0.7.post1)
Requires-Dist: entrypoints (==0.3)
Requires-Dist: fastscript (==0.1.4)
Requires-Dist: future (==0.18.2)
Requires-Dist: graphviz (==0.14)
Requires-Dist: importlib-metadata (==1.6.0)
Requires-Dist: ipykernel (==5.3.0)
Requires-Dist: ipython (==7.15.0)
Requires-Dist: ipython-genutils (==0.2.0)
Requires-Dist: ipywidgets (==7.5.1)
Requires-Dist: jedi (==0.17.0)
Requires-Dist: Jinja2 (==2.11.2)
Requires-Dist: joblib (==0.15.1)
Requires-Dist: jsonschema (==3.2.0)
Requires-Dist: jupyter (==1.0.0)
Requires-Dist: jupyter-client (==6.1.3)
Requires-Dist: jupyter-console (==6.1.0)
Requires-Dist: jupyter-core (==4.6.3)
Requires-Dist: MarkupSafe (==1.1.1)
Requires-Dist: mip (==1.9.1)
Requires-Dist: mistune (==0.8.4)
Requires-Dist: nbconvert (==5.6.1)
Requires-Dist: nbdev (==0.2.18)
Requires-Dist: nbformat (==5.0.6)
Requires-Dist: notebook (==6.0.3)
Requires-Dist: numpy (==1.18.5)
Requires-Dist: osqp (==0.6.1)
Requires-Dist: packaging (==20.4)
Requires-Dist: pandas (==1.0.4)
Requires-Dist: pandocfilters (==1.4.2)
Requires-Dist: parso (==0.7.0)
Requires-Dist: pexpect (==4.8.0)
Requires-Dist: pickleshare (==0.7.5)
Requires-Dist: prometheus-client (==0.8.0)
Requires-Dist: prompt-toolkit (==3.0.5)
Requires-Dist: ptyprocess (==0.6.0)
Requires-Dist: pycparser (==2.20)
Requires-Dist: Pygments (==2.6.1)
Requires-Dist: pyparsing (==2.4.7)
Requires-Dist: pyrsistent (==0.16.0)
Requires-Dist: python-dateutil (==2.8.1)
Requires-Dist: pytz (==2020.1)
Requires-Dist: PyYAML (==5.3.1)
Requires-Dist: pyzmq (==19.0.1)
Requires-Dist: qtconsole (==4.7.4)
Requires-Dist: QtPy (==1.9.0)
Requires-Dist: scikit-learn (==0.23.1)
Requires-Dist: scipy (==1.4.1)
Requires-Dist: scs (==2.1.2)
Requires-Dist: Send2Trash (==1.5.0)
Requires-Dist: six (==1.15.0)
Requires-Dist: terminado (==0.8.3)
Requires-Dist: testpath (==0.4.4)
Requires-Dist: threadpoolctl (==2.1.0)
Requires-Dist: tornado (==6.0.4)
Requires-Dist: traitlets (==4.3.3)
Requires-Dist: wcwidth (==0.2.3)
Requires-Dist: webencodings (==0.5.1)
Requires-Dist: widgetsnbextension (==3.5.1)
Requires-Dist: zipp (==3.1.0)
